[
  {
    "entity": "User",
    "apis": [
      {
        "name": "Create User",
        "method": "POST",
        "url": "/auth/register",
        "isTokenNeed": true,
        "body": {
          "username": "",
          "email": "",
          "password": ""
        }
      },
      {
        "name": "Get Users",
        "method": "POST",
        "url": "/auth/login"
      },
      {
        "name": "Get Login",
        "method": "POST",
        "url": "/auth/login",
        "isTokenNeed": true,
        "body": {
          "email": "",
          "password": ""
        }
      },
      {
        "name": "Delete User",
        "method": "DELETE",
        "url": "/auth/user/:id"
      }
    ]
  },
  {
    "entity": "Institute",
    "apis": [
      {
        "name": "Create Institute",
        "method": "POST",
        "url": "/api/institute",
        "isTokenNeed": true,
        "body": {
          "instituteName": ""
        }
      },
      {
        "name": "Get Institute",
        "method": "GET",
        "url": "/api/institute/:id"
      },
      {
        "name": "Update Institute",
        "method": "PUT",
        "url": "/api/institute/:id",
        "isTokenNeed": true,
        "body": {}
      },
      {
        "name": "Delete Institute",
        "method": "DELETE",
        "url": "/api/institute/:id"
      }
    ]
  },
  {
    "entity": "Teacher",
    "apis": [
      {
        "name": "Create Teacher",
        "method": "POST",
        "url": "/api/teacher",
        "isTokenNeed": true,
        "body": {}
      },
      {
        "name": "Get Teacher",
        "method": "GET",
        "url": "/api/teacher/:id"
      },
      {
        "name": "Update Teacher",
        "method": "PUT",
        "url": "/api/teacher/:id",
        "isTokenNeed": true,
        "body": {}
      },
      {
        "name": "Delete Teacher",
        "method": "DELETE",
        "url": "/api/teacher/:id"
      }
    ]
  },
  {
    "entity": "Student",
    "apis": [
      {
        "name": "Create Student",
        "method": "POST",
        "url": "/api/student",
        "isTokenNeed": true,
        "body": {}
      },
      {
        "name": "Get Student",
        "method": "GET",
        "url": "/api/student/:id"
      },
      {
        "name": "Update Student",
        "method": "PUT",
        "url": "/api/student/:id",
        "isTokenNeed": true,
        "body": {}
      },
      {
        "name": "Delete Student",
        "method": "DELETE",
        "url": "/api/student/:id"
      }
    ]
  },
  {
    "entity": "Course",
    "apis": [
      {
        "name": "Create Course",
        "method": "POST",
        "url": "/api/course",
        "isTokenNeed": true,
        "body": {}
      },
      {
        "name": "Get Course",
        "method": "GET",
        "url": "/api/course/:id"
      },
      {
        "name": "Update Course",
        "method": "PUT",
        "url": "/api/course/:id",
        "isTokenNeed": true,
        "body": {}
      },
      {
        "name": "Delete Course",
        "method": "DELETE",
        "url": "/api/course/:id"
      }
    ]
  },
  {
    "entity": "Cart",
    "apis": [
      {
        "name": "Add to Cart",
        "method": "POST",
        "url": "/api/cart",
        "isTokenNeed": true,
        "body": {}
      },
      {
        "name": "Get Cart",
        "method": "GET",
        "url": "/api/cart/:id"
      },
      {
        "name": "Update Cart",
        "method": "PUT",
        "url": "/api/cart/:id",
        "isTokenNeed": true,
        "body": {}
      },
      {
        "name": "Delete Cart",
        "method": "DELETE",
        "url": "/api/cart/:id"
      }
    ]
  },
  {
    "entity": "Order",
    "apis": [
      {
        "name": "Create Order",
        "method": "POST",
        "url": "/api/order",
        "isTokenNeed": true,
        "body": {}
      },
      {
        "name": "Get Order",
        "method": "GET",
        "url": "/api/order/:id"
      },
      {
        "name": "Update Order",
        "method": "PUT",
        "url": "/api/order/:id",
        "isTokenNeed": true,
        "body": {}
      },
      {
        "name": "Delete Order",
        "method": "DELETE",
        "url": "/api/order/:id"
      }
    ]
  }
]